hmi_rabbitmq/__init__.py
hmi_rabbitmq/chart.py
hmi_rabbitmq/configfile.py
hmi_rabbitmq/py.typed
hmi_rabbitmq/private/__init__.py
hmi_rabbitmq/private/chart.py
hmi_rabbitmq/tests/__init__.py
hmi_rabbitmq/tests/test_chart.py
hmi_rabbitmq-0.8.1.dist-info/LICENSE
hmi_rabbitmq-0.8.1.dist-info/METADATA
hmi_rabbitmq-0.8.1.dist-info/WHEEL
hmi_rabbitmq-0.8.1.dist-info/top_level.txt
hmi_rabbitmq-0.8.1.dist-info/RECORD
