Metadata-Version: 2.1
Name: hmi-rabbitmq
Version: 0.8.1
Summary: Helmion Plugin: RabbitMQ
Home-page: https://github.com/RangelReale/hmi_rabbitmq
Author: Rangel Reale
Author-email: rangelreale@gmail.com
License: UNKNOWN
Platform: UNKNOWN
Classifier: Programming Language :: Python :: 3
Classifier: License :: OSI Approved :: MIT License
Classifier: Operating System :: OS Independent
Requires-Python: >=3.6
Requires-Dist: helmion (>=0.8.4)
Requires-Dist: deepmerge (>=0.1)
Requires-Dist: kubragen2 (>=0.8.1)
